gapipy/__init__.py
gapipy/cache.py
gapipy/client.py
gapipy/query.py
gapipy/request.py
gapipy/utils.py
gapipy/models/__init__.py
gapipy/models/addon.py
gapipy/models/address.py
gapipy/models/advertised_departure.py
gapipy/models/agency_document.py
gapipy/models/arrival_flight_detail.py
gapipy/models/associated_service.py
gapipy/models/base.py
gapipy/models/departure_flight_detail.py
gapipy/models/departure_service_room.py
gapipy/models/document_info.py
gapipy/models/dossier_feature.py
gapipy/models/incomplete_requirement.py
gapipy/models/international_ticket_number.py
gapipy/models/price_band.py
gapipy/models/price_promotion.py
gapipy/models/room.py
gapipy/models/traveller_height.py
gapipy/resources/__init__.py
gapipy/resources/base.py
gapipy/resources/language.py
gapipy/resources/booking/__init__.py
gapipy/resources/booking/agency.py
gapipy/resources/booking/agent.py
gapipy/resources/booking/booking.py
gapipy/resources/booking/customer.py
gapipy/resources/booking/declined_reason.py
gapipy/resources/booking/document.py
gapipy/resources/booking/nationality.py
gapipy/resources/booking/service.py
gapipy/resources/booking/transaction.py
gapipy/resources/dossier/__init__.py
gapipy/resources/dossier/accommodation_dossier.py
gapipy/resources/dossier/activity_dossier.py
gapipy/resources/dossier/details.py
gapipy/resources/dossier/dossier_features.py
gapipy/resources/dossier/place_dossier.py
gapipy/resources/dossier/transport_dossier.py
gapipy/resources/geo/__init__.py
gapipy/resources/geo/airport.py
gapipy/resources/geo/continent.py
gapipy/resources/geo/country.py
gapipy/resources/geo/feature.py
gapipy/resources/geo/feature_category.py
gapipy/resources/geo/place.py
gapipy/resources/geo/state.py
gapipy/resources/geo/timezone.py
gapipy/resources/tour/__init__.py
gapipy/resources/tour/accommodation.py
gapipy/resources/tour/activity.py
gapipy/resources/tour/departure.py
gapipy/resources/tour/departure_component.py
gapipy-2.0.0.dist-info/DESCRIPTION.rst
gapipy-2.0.0.dist-info/METADATA
gapipy-2.0.0.dist-info/metadata.json
gapipy-2.0.0.dist-info/RECORD
gapipy-2.0.0.dist-info/top_level.txt
gapipy-2.0.0.dist-info/WHEEL
