Metadata-Version: 2.0
Name: gapipy
Version: 2.0.0
Summary: Python client for the G Adventures REST API
Home-page: https://github.com/gadventures/gapipy
Author: G Adventures
Author-email: software@gadventures.com
License: MIT
Keywords: gapipy
Platform: UNKNOWN
Classifier: Development Status :: 4 - Beta
Classifier: Intended Audience :: Developers
Classifier: License :: OSI Approved :: MIT License
Classifier: Natural Language :: English
Classifier: Programming Language :: Python :: 2
Classifier: Programming Language :: Python :: 2.7
Requires-Dist: requests
